{
  "BundleId": "QuestBundle_S7_Week_001",
  "BundleSchedule": "Season7_Free_Schedule",
  "BundleRequired": {
    "RequiredLevel": 1
  },
  "BundlesObject": [
    {
      "templateId": "Quest:Quest_BR_Collect_Item_All_Rarity",
      "quest_data": {
        "RequireBP": false,
        "ExtraQuests": false,
        "IsWeekly": true
      },
      "Rewards": {
        "BattleStars": 5,
        "Quest": [],
        "GrantedItems": []
      },
      "Objectives": [
        {
          "BackendName": "battlepass_collect_all_rarity_common",
          "Count": 1,
          "Stage": -1
        },
        {
          "BackendName": "battlepass_collect_all_rarity_uncommon",
          "Count": 1,
          "Stage": -1
        },
        {
          "BackendName": "battlepass_collect_all_rarity_rare",
          "Count": 1,
          "Stage": -1
        },
        {
          "BackendName": "battlepass_collect_all_rarity_very_rare",
          "Count": 1,
          "Stage": -1
        },
        {
          "BackendName": "battlepass_collect_all_super_rare",
          "Count": 1,
          "Stage": -1
        }
      ]
    },
    {
      "templateId": "Quest:Quest_BR_Dance_ScavengerHunt_Forbidden",
      "quest_data": {
        "RequireBP": false,
        "ExtraQuests": false,
        "IsWeekly": true
      },
      "Rewards": {
        "BattleStars": 5,
        "Quest": [],
        "GrantedItems": []
      },
      "Objectives": [
        {
          "BackendName": "battlepass_dance_athena_location_forbidden_01",
          "Count": 1,
          "Stage": -1
        },
        {
          "BackendName": "battlepass_dance_athena_location_forbidden_02",
          "Count": 1,
          "Stage": -1
        },
        {
          "BackendName": "battlepass_dance_athena_location_forbidden_03",
          "Count": 1,
          "Stage": -1
        },
        {
          "BackendName": "battlepass_dance_athena_location_forbidden_04",
          "Count": 1,
          "Stage": -1
        },
        {
          "BackendName": "battlepass_dance_athena_location_forbidden_05",
          "Count": 1,
          "Stage": -1
        },
        {
          "BackendName": "battlepass_dance_athena_location_forbidden_06",
          "Count": 1,
          "Stage": -1
        },
        {
          "BackendName": "battlepass_dance_athena_location_forbidden_07",
          "Count": 1,
          "Stage": -1
        },
        {
          "BackendName": "battlepass_dance_athena_location_forbidden_08",
          "Count": 1,
          "Stage": -1
        },
        {
          "BackendName": "battlepass_dance_athena_location_forbidden_09",
          "Count": 1,
          "Stage": -1
        },
        {
          "BackendName": "battlepass_dance_athena_location_forbidden_10",
          "Count": 1,
          "Stage": -1
        },
        {
          "BackendName": "battlepass_dance_athena_location_forbidden_11",
          "Count": 1,
          "Stage": -1
        },
        {
          "BackendName": "battlepass_dance_athena_location_forbidden_12",
          "Count": 1,
          "Stage": -1
        },
        {
          "BackendName": "battlepass_dance_athena_location_forbidden_13",
          "Count": 1,
          "Stage": -1
        },
        {
          "BackendName": "battlepass_dance_athena_location_forbidden_14",
          "Count": 1,
          "Stage": -1
        },
        {
          "BackendName": "battlepass_dance_athena_location_forbidden_15",
          "Count": 1,
          "Stage": -1
        }
      ]
    },
    {
      "templateId": "Quest:Quest_BR_Play_Min1Elimination",
      "quest_data": {
        "RequireBP": false,
        "ExtraQuests": false,
        "IsWeekly": true
      },
      "Rewards": {
        "BattleStars": 10,
        "Quest": [],
        "GrantedItems": []
      },
      "Objectives": [
        {
          "BackendName": "battlepass_complete_athena_with_killingblow",
          "Count": 5,
          "Stage": -1
        }
      ]
    },
    {
      "templateId": "Quest:Quest_BR_Dance_Chain_ScavengerHunt_Locations_A",
      "quest_data": {
        "RequireBP": true,
        "ExtraQuests": false,
        "IsWeekly": true,
        "Steps": true
      },
      "Rewards": {
        "BattleStars": 1,
        "Quest": [
          {
            "TemplateId": "Quest:Quest_BR_Dance_Chain_ScavengerHunt_Locations_B",
            "Quantity": 1
          }
        ],
        "GrantedItems": []
      },
      "Objectives": [
        {
          "BackendName": "battlepass_dance_chain_athena_scavengerhunt_locations_a",
          "Count": 1,
          "Stage": -1
        }
      ]
    },
    {
      "templateId": "Quest:Quest_BR_Dance_Chain_ScavengerHunt_Locations_B",
      "quest_data": {
        "RequireBP": true,
        "ExtraQuests": true,
        "Steps": true
      },
      "Rewards": {
        "BattleStars": 2,
        "Quest": [
          {
            "TemplateId": "Quest:Quest_BR_Dance_Chain_ScavengerHunt_Locations_C",
            "Quantity": 1
          }
        ],
        "GrantedItems": []
      },
      "Objectives": [
        {
          "BackendName": "battlepass_dance_chain_athena_scavengerhunt_locations_b",
          "Count": 1,
          "Stage": -1
        }
      ]
    },
    {
      "templateId": "Quest:Quest_BR_Dance_Chain_ScavengerHunt_Locations_C",
      "quest_data": {
        "RequireBP": true,
        "ExtraQuests": true,
        "Steps": false
      },
      "Rewards": {
        "BattleStars": 2,
        "Quest": [],
        "GrantedItems": []
      },
      "Objectives": [
        {
          "BackendName": "battlepass_dance_chain_athena_scavengerhunt_locations_c",
          "Count": 1,
          "Stage": -1
        }
      ]
    },
    {
      "templateId": "Quest:Quest_BR_Damage_Headshot",
      "quest_data": {
        "RequireBP": true,
        "ExtraQuests": false,
        "IsWeekly": true
      },
      "Rewards": {
        "BattleStars": 5,
        "Quest": [],
        "GrantedItems": []
      },
      "Objectives": [
        {
          "BackendName": "battlepass_damage_athena_player_head_shots",
          "Count": 500,
          "Stage": -1
        }
      ]
    },
    {
      "templateId": "Quest:Quest_BR_Interact_Chain_Chests_Search_A",
      "quest_data": {
        "RequireBP": true,
        "ExtraQuests": false,
        "IsWeekly": true,
        "Steps": true
      },
      "Rewards": {
        "BattleStars": 3,
        "Quest": [
          {
            "TemplateId": "Quest:Quest_BR_Interact_Chain_Chests_Search_B",
            "Quantity": 1
          }
        ],
        "GrantedItems": []
      },
      "Objectives": [
        {
          "BackendName": "battlepass_chain_chests_search_a",
          "Count": 5,
          "Stage": -1
        }
      ]
    },
    {
      "templateId": "Quest:Quest_BR_Interact_Chain_Chests_Search_B",
      "quest_data": {
        "RequireBP": true,
        "ExtraQuests": true,
        "Steps": true
      },
      "Rewards": {
        "BattleStars": 3,
        "Quest": [
          {
            "TemplateId": "Quest:Quest_BR_Interact_Chain_Chests_Search_C",
            "Quantity": 1
          }
        ],
        "GrantedItems": []
      },
      "Objectives": [
        {
          "BackendName": "battlepass_chain_chests_search_b",
          "Count": 3,
          "Stage": -1
        }
      ]
    },
    {
      "templateId": "Quest:Quest_BR_Interact_Chain_Chests_Search_C",
      "quest_data": {
        "RequireBP": true,
        "ExtraQuests": true,
        "Steps": false
      },
      "Rewards": {
        "BattleStars": 4,
        "Quest": [],
        "GrantedItems": []
      },
      "Objectives": [
        {
          "BackendName": "battlepass_chain_chests_search_c",
          "Count": 1,
          "Stage": -1
        }
      ]
    },
    {
      "templateId": "Quest:Quest_BR_Eliminate_Location_Different",
      "quest_data": {
        "RequireBP": true,
        "ExtraQuests": false,
        "IsWeekly": true
      },
      "Rewards": {
        "BattleStars": 10,
        "Quest": [],
        "GrantedItems": []
      },
      "Objectives": [
        {
          "BackendName": "battlepass_killingblow_athena_player_different_junkjunction",
          "Count": 1,
          "Stage": -1
        },
        {
          "BackendName": "battlepass_killingblow_athena_player_different_hauntedhills",
          "Count": 1,
          "Stage": -1
        },
        {
          "BackendName": "battlepass_killingblow_athena_player_different_pleasantpartk",
          "Count": 1,
          "Stage": -1
        },
        {
          "BackendName": "battlepass_killingblow_athena_player_different_lootlake",
          "Count": 1,
          "Stage": -1
        },
        {
          "BackendName": "battlepass_killingblow_athena_player_different_lazylinks",
          "Count": 1,
          "Stage": -1
        },
        {
          "BackendName": "battlepass_killingblow_athena_player_different_tomatotemple",
          "Count": 1,
          "Stage": -1
        },
        {
          "BackendName": "battlepass_killingblow_athena_player_different_riskyreels",
          "Count": 1,
          "Stage": -1
        },
        {
          "BackendName": "battlepass_killingblow_athena_player_different_wailingwoods",
          "Count": 1,
          "Stage": -1
        },
        {
          "BackendName": "battlepass_killingblow_athena_player_different_snobbyshores",
          "Count": 1,
          "Stage": -1
        },
        {
          "BackendName": "battlepass_killingblow_athena_player_different_greasygrove",
          "Count": 1,
          "Stage": -1
        },
        {
          "BackendName": "battlepass_killingblow_athena_player_different_tiltedtowers",
          "Count": 1,
          "Stage": -1
        },
        {
          "BackendName": "battlepass_killingblow_athena_player_different_shiftyshafts",
          "Count": 1,
          "Stage": -1
        },
        {
          "BackendName": "battlepass_killingblow_athena_player_different_dustydivot",
          "Count": 1,
          "Stage": -1
        },
        {
          "BackendName": "battlepass_killingblow_athena_player_different_saltysprings",
          "Count": 1,
          "Stage": -1
        },
        {
          "BackendName": "battlepass_killingblow_athena_player_different_retailrow",
          "Count": 1,
          "Stage": -1
        },
        {
          "BackendName": "battlepass_killingblow_athena_player_different_lonelylodge",
          "Count": 1,
          "Stage": -1
        },
        {
          "BackendName": "battlepass_killingblow_athena_player_different_flushfactory",
          "Count": 1,
          "Stage": -1
        },
        {
          "BackendName": "battlepass_killingblow_athena_player_different_luckylanding",
          "Count": 1,
          "Stage": -1
        },
        {
          "BackendName": "battlepass_killingblow_athena_player_different_fatalfields",
          "Count": 1,
          "Stage": -1
        },
        {
          "BackendName": "battlepass_killingblow_athena_player_different_paradisepalms",
          "Count": 1,
          "Stage": -1
        },
        {
          "BackendName": "battlepass_killingblow_athena_player_different_polarpeak",
          "Count": 1,
          "Stage": -1
        },
        {
          "BackendName": "battlepass_killingblow_athena_player_different_frostyflights",
          "Count": 1,
          "Stage": -1
        },
        {
          "BackendName": "battlepass_killingblow_athena_player_different_happyhamlet",
          "Count": 1,
          "Stage": -1
        }
      ]
    }
  ]
}